[
  {
    "id": 1043,
    "imdb_id": "tt17372926",
    "tmdb_id": "1014063",
    "title": "AT THE GATES",
    "poster": "https://www.themoviedb.org/t/p/w500/kOSRXwB7WLn3tq5DYT6qvTe7U82.jpg",
    "release_date": "11/3/23"
  },
  {
    "id": 1044,
    "imdb_id": "tt15091524",
    "tmdb_id": "912600",
    "title": "SOME OTHER WOMAN",
    "poster": "https://www.themoviedb.org/t/p/w500/kiXZm4lEuE5DbvUssNFi10X3J4J.jpg",
    "release_date": "1/5/24"
  },
  {
    "id": 1045,
    "imdb_id": "tt2263648",
    "tmdb_id": "476928",
    "title": "WHAT ABOUT LOVE",
    "poster": "https://www.themoviedb.org/t/p/w500/jGVpMWEemYCSa2p9OSCMsaBXY98.jpg",
    "release_date": "2/14/24"
  },
  {
    "id": 1046,
    "imdb_id": "tt12004238",
    "tmdb_id": "680027",
    "title": "ALTERED REALITY",
    "poster": "https://www.themoviedb.org/t/p/w500/5SWMAhFwRYS3VbGwIv1j2DySYMG.jpg",
    "release_date": "2/16/24"
  },
  {
    "id": 1047,
    "imdb_id": "tt14356266",
    "tmdb_id": "1223440",
    "title": "THE NEON HIGHWAY",
    "poster": "https://www.themoviedb.org/t/p/w500/myFLl70Jg2DhJ6emvMEFMiD2tOg.jpg",
    "release_date": "2/27/24"
  },
  {
    "id": 1048,
    "imdb_id": "tt9352178",
    "tmdb_id": "632995",
    "title": "THE PRIMEVALS",
    "poster": "https://www.themoviedb.org/t/p/w500/6Y96O3T4i2ZoCrKemYjxfnU63Iu.jpg",
    "release_date": "3/11/24"
  },
  {
    "id": 1049,
    "imdb_id": "tt24806518",
    "tmdb_id": "1063679",
    "title": "FREE TIME",
    "poster": "https://www.themoviedb.org/t/p/w500/nO7inolIFHkNUAklk1iHdfPfHlr.jpg",
    "release_date": "3/22/24"
  },
  {
    "id": 1050,
    "imdb_id": "tt24244436",
    "tmdb_id": "1081593",
    "title": "HOUSEKEEPING FOR BEGINNERS",
    "poster": "https://www.themoviedb.org/t/p/w500/fXg7Avh7eQzkeasMqwGiDxlQRqi.jpg",
    "release_date": "4/5/24"
  },
  {
    "id": 1051,
    "imdb_id": "tt21651430",
    "tmdb_id": "808482",
    "title": "THE PEOPLE'S JOKER",
    "poster": "https://www.themoviedb.org/t/p/w500/9mPoxHqonXXeQnwscNEd73Z0Ik3.jpg",
    "release_date": "4/5/24"
  },
  {
    "id": 1052,
    "imdb_id": "tt30180830",
    "tmdb_id": "1015634",
    "title": "SASQUATCH SUNSET",
    "poster": "https://www.themoviedb.org/t/p/w500/s43rgDGRDOB12prgK9YfWPEIyAh.jpg",
    "release_date": "4/12/24"
  },
  {
    "id": 1053,
    "imdb_id": "tt20112746",
    "tmdb_id": "1087388",
    "title": "STING",
    "poster": "https://www.themoviedb.org/t/p/w500/zuSAZIG1PSrxFwPeAlGtg9LTwxo.jpg",
    "release_date": "4/12/24"
  },
  {
    "id": 1054,
    "imdb_id": "tt12444168",
    "tmdb_id": "1251687",
    "title": "DON'T TELL MOM THE BABYSITTER'S DEAD",
    "poster": "https://www.themoviedb.org/t/p/w500/jRhyL0c6E06nX5RZxrk9w5kzord.jpg",
    "release_date": "4/12/24"
  },
  {
    "id": 1055,
    "imdb_id": "tt15353574",
    "tmdb_id": "1009679",
    "title": "HARD MILES",
    "poster": "https://www.themoviedb.org/t/p/w500/pU50LpVZ7doTyJeC9JaqcbeH4ef.jpg",
    "release_date": "4/19/24"
  },
  {
    "id": 1056,
    "imdb_id": "tt28639049",
    "tmdb_id": "1163186",
    "title": "WE GROWN NOW",
    "poster": "https://www.themoviedb.org/t/p/w500/oPGc7D4rlSoW4tvGS3ZvlG2wfmn.jpg",
    "release_date": "4/19/24"
  },
  {
    "id": 1057,
    "imdb_id": "tt30319533",
    "tmdb_id": "1214474",
    "title": "STRESS POSITIONS",
    "poster": "https://www.themoviedb.org/t/p/w500/lXfh0bSMc8BcpUyaddZYmfsWwbs.jpg",
    "release_date": "4/19/24"
  },
  {
    "id": 1058,
    "imdb_id": "tt23638614",
    "tmdb_id": "1115009",
    "title": "UNSUNG HERO",
    "poster": "https://www.themoviedb.org/t/p/w500/wKYrat0neU4sHl8aO4BCzxCKFQy.jpg",
    "release_date": "4/26/24"
  },
  {
    "id": 1059,
    "imdb_id": "tt16426418",
    "tmdb_id": "937287",
    "title": "CHALLENGERS",
    "poster": "https://www.themoviedb.org/t/p/w500/H6vke7zGiuLsz4v4RPeReb9rsv.jpg",
    "release_date": "4/26/24"
  },
  {
    "id": 1060,
    "imdb_id": "tt27722061",
    "tmdb_id": "1059319",
    "title": "THE FEELING THAT THE TIME FOR DOING SOMETHING HAS PASSED",
    "poster": "https://www.themoviedb.org/t/p/w500/739T9ieCKgPvmZfzQzYl9dyX6cp.jpg",
    "release_date": "4/26/24"
  },
  {
    "id": 1061,
    "imdb_id": "tt27507837",
    "tmdb_id": "1115579",
    "title": "LOST SOULZ",
    "poster": "https://www.themoviedb.org/t/p/w500/fFYgnBCTDONhMw3qW3um0LovBFM.jpg",
    "release_date": "5/3/24"
  },
  {
    "id": 1062,
    "imdb_id": "tt15574270",
    "tmdb_id": "858017",
    "title": "I SAW THE TV GLOW",
    "poster": "https://www.themoviedb.org/t/p/w500/hS4GYkYpN1rfl4GIxyc02sCyfAj.jpg",
    "release_date": "5/3/24"
  },
  {
    "id": 1063,
    "imdb_id": "tt26442871",
    "tmdb_id": "1076101",
    "title": "WILDCAT",
    "poster": "https://www.themoviedb.org/t/p/w500/qRFlDK9cXKNF3UU1E567ZpsC4Rq.jpg",
    "release_date": "5/3/24"
  },
  {
    "id": 1064,
    "imdb_id": "tt11389872",
    "tmdb_id": "653346",
    "title": "KINGDOM OF THE PLANET OF THE APES",
    "poster": "https://www.themoviedb.org/t/p/w500/gKkl37BQuKTanygYQG1pyYgLVgf.jpg",
    "release_date": "5/10/24"
  },
  {
    "id": 1065,
    "imdb_id": "tt28494031",
    "tmdb_id": "1156110",
    "title": "GASOLINE RAINBOW",
    "poster": "https://www.themoviedb.org/t/p/w500/3wZPMKCrL4jwpAMWgQQoV75VaU.jpg",
    "release_date": "5/10/24"
  },
  {
    "id": 1066,
    "imdb_id": "tt19358036",
    "tmdb_id": "1045467",
    "title": "NOT ANOTHER CHURCH MOVIE",
    "poster": "https://www.themoviedb.org/t/p/w500/1EJ3MhWGnWNXLgmWXb4e3QGb1m1.jpg",
    "release_date": "5/10/24"
  },
  {
    "id": 1067,
    "imdb_id": "tt18077924",
    "tmdb_id": "834562",
    "title": "POOLMAN",
    "poster": "https://www.themoviedb.org/t/p/w500/vVz4Rh4j6FQTq9eva3xEvCMumAh.jpg",
    "release_date": "5/10/24"
  },
  {
    "id": 1068,
    "imdb_id": "tt28332336",
    "tmdb_id": "1183002",
    "title": "THE IMAGE OF YOU",
    "poster": "https://www.themoviedb.org/t/p/w500/gboq2oB6QNBcW32V0A8uOajTwXU.jpg",
    "release_date": "5/10/24"
  }
]